setup.py
MiniMockTest.egg-info/PKG-INFO
MiniMockTest.egg-info/SOURCES.txt
MiniMockTest.egg-info/dependency_links.txt
MiniMockTest.egg-info/entry_points.txt
MiniMockTest.egg-info/top_level.txt
MiniMockTest.egg-info/zip-safe
minimocktest/__init__.py
minimocktest/minimock.py