Metadata-Version: 1.0
Name: MiniMockTest
Version: 0.5
Summary: Custom unittest TestCase that wraps minimock
Home-page: http://pykler.github.com/MiniMockTest/
Author: Hatem Nassrat
Author-email: hnassrat@gmail.com
License: MIT
Keywords: minimock mock mocking test unittest TestCase MockTestCase
Platform: UNKNOWN
